{
  "aliases": {
    "ll": {
      "command": "ls -lah",
      "category": "general"
    },
    "dps": {
      "command": "docker ps",
      "category": "docker"
    },
    "gst": {
      "command": "git status",
      "category": "git"
    },
    "gco": {
      "command": "git checkout",
      "category": "git"
    },
    "glog": {
      "command": "git log --oneline --graph --decorate",
      "category": "git"
    },
    "hg": {
      "command": "history | grep",
      "category": "general"
    },
    "tba": {
      "command": "turboalias",
      "category": "general"
    },
    "testsynch": {
      "command": "echo sync works",
      "category": "test"
    },
    "noautosync": {
      "command": "echo no auto",
      "category": null
    },
    "gsync": {
      "command": "git add . && git commit -m \"sync\" && git push",
      "category": "git"
    },
    "testchange": {
      "command": "echo test",
      "category": "test"
    },
    "autotest1": {
      "command": "echo auto sync test 1",
      "category": "test"
    },
    "autotest2": {
      "command": "echo auto sync test 2",
      "category": "test"
    },
    "synctest": {
      "command": "echo sync works!",
      "category": null
    },
    "autotest": {
      "command": "echo auto-sync test",
      "category": null
    },
    "finaltest": {
      "command": "echo final test",
      "category": null
    },
    "test2": {
      "command": "echo test2",
      "category": null
    },
    "test3": {
      "command": "echo test3",
      "category": null
    },
    "autosynctest": {
      "command": "echo auto sync is working",
      "category": "test"
    },
    "autosynctest2": {
      "command": "echo second test",
      "category": "test"
    },
    "autosynctest3": {
      "command": "echo third test works!",
      "category": "test"
    }
  },
  "categories": {
    "general": [
      "ll",
      "hg",
      "tba"
    ],
    "docker": [
      "dps"
    ],
    "git": [
      "gst",
      "gco",
      "glog",
      "gsync"
    ],
    "test": [
      "testsynch",
      "testchange",
      "autotest1",
      "autotest2",
      "autosynctest",
      "autosynctest2",
      "autosynctest3"
    ]
  }
}